pascalnobereit_langchain_google_vertexai/__init__.py
pascalnobereit_langchain_google_vertexai/_base.py
pascalnobereit_langchain_google_vertexai/_enums.py
pascalnobereit_langchain_google_vertexai/_image_utils.py
pascalnobereit_langchain_google_vertexai/_utils.py
pascalnobereit_langchain_google_vertexai/callbacks.py
pascalnobereit_langchain_google_vertexai/chains.py
pascalnobereit_langchain_google_vertexai/chat_models.py
pascalnobereit_langchain_google_vertexai/embeddings.py
pascalnobereit_langchain_google_vertexai/functions_utils.py
pascalnobereit_langchain_google_vertexai/gemma.py
pascalnobereit_langchain_google_vertexai/llms.py
pascalnobereit_langchain_google_vertexai/model_garden.py
pascalnobereit_langchain_google_vertexai/py.typed
pascalnobereit_langchain_google_vertexai/vectorstores/__init__.py
pascalnobereit_langchain_google_vertexai/vectorstores/_document_storage.py
pascalnobereit_langchain_google_vertexai/vectorstores/_sdk_manager.py
pascalnobereit_langchain_google_vertexai/vectorstores/_searcher.py
pascalnobereit_langchain_google_vertexai/vectorstores/_utils.py
pascalnobereit_langchain_google_vertexai/vectorstores/vectorstores.py
pascalnobereit_langchain_google_vertexai/vision_models.py
pascalnobereit_langchain_google_vertexai-0.1.4.dist-info/LICENSE
pascalnobereit_langchain_google_vertexai-0.1.4.dist-info/METADATA
pascalnobereit_langchain_google_vertexai-0.1.4.dist-info/WHEEL
pascalnobereit_langchain_google_vertexai-0.1.4.dist-info/RECORD
