Metadata-Version: 2.1
Name: pascalnobereit-langchain-google-vertexai
Version: 0.1.4
Summary: An integration package connecting Google VertexAI and LangChain
Home-page: https://github.com/langchain-ai/langchain-google
License: MIT
Requires-Python: >=3.8.1,<4.0
Classifier: License :: OSI Approved :: MIT License
Classifier: Programming Language :: Python :: 3
Classifier: Programming Language :: Python :: 3.9
Classifier: Programming Language :: Python :: 3.10
Classifier: Programming Language :: Python :: 3.11
Classifier: Programming Language :: Python :: 3.12
Requires-Dist: google-cloud-aiplatform (>=1.44.0,<2.0.0)
Requires-Dist: google-cloud-storage (>=2.14.0,<3.0.0)
Requires-Dist: langchain (>=0.1.11,<0.2.0)
Requires-Dist: langchain-community (>=0.0.27,<0.0.28)
Requires-Dist: langchain-core (>=0.1.27,<0.2)
Requires-Dist: types-protobuf (>=4.24.0.4,<5.0.0.0)
Requires-Dist: types-requests (>=2.31.0,<3.0.0)
Project-URL: Repository, https://github.com/langchain-ai/langchain-google
Project-URL: Source Code, https://github.com/langchain-ai/langchain-google/tree/main/libs/vertexai
